simple_wait/__init__.py
simple_wait-1.0.8.dist-info/LICENSE.txt
simple_wait-1.0.8.dist-info/METADATA
simple_wait-1.0.8.dist-info/WHEEL
simple_wait-1.0.8.dist-info/top_level.txt
simple_wait-1.0.8.dist-info/RECORD
