Metadata-Version: 2.1
Name: simple-wait
Version: 1.0.8
Summary: Simple wait
Author-email: Ilya Petrash <ilya.petrash@inbox.ru>
License: MIT License
Project-URL: Homepage, https://github.com/gil9red/simple-wait
Project-URL: Bug Tracker, https://github.com/gil9red/simple-wait/issues
Keywords: wait
Classifier: Programming Language :: Python :: 3
Classifier: License :: OSI Approved :: MIT License
Classifier: Operating System :: OS Independent
Classifier: Topic :: Software Development :: Libraries :: Python Modules
Requires-Python: >=3.9
License-File: LICENSE.txt
